chinillaclvm_rs-0.1.24.dist-info/METADATA
chinillaclvm_rs-0.1.24.dist-info/WHEEL
chinillaclvm_rs/__init__.py
chinillaclvm_rs/chinillaclvm_rs.abi3.so
chinillaclvm_rs-0.1.24.dist-info/RECORD
