Metadata-Version: 2.1
Name: chinillaclvm_rs
Version: 0.1.24
Summary: Implementation of `chinillaclvm` for Chinilla Network's cryptocurrency
Home-Page: https://github.com/Chinilla/chinillaclvm_rs/
Author: Richard Kiss <him@richardkiss.com>
Author-email: Richard Kiss <him@richardkiss.com>
License: Apache-2.0
Project-URL: Source Code, https://github.com/Chinilla/chinillaclvm_rs/
